tonconsole/__init__.py
tonconsole/tonapi/__init__.py
tonconsole/tonapi/exceptions.py
tonconsole/tonapi/utils.py
tonconsole/tonapi/async_tonapi/__init__.py
tonconsole/tonapi/async_tonapi/client.py
tonconsole/tonapi/async_tonapi/methods/__init__.py
tonconsole/tonapi/async_tonapi/methods/accounts.py
tonconsole/tonapi/async_tonapi/methods/jettons.py
tonconsole/tonapi/async_tonapi/methods/nfts.py
tonconsole/tonapi/async_tonapi/methods/traces.py
tonconsole/tonapi/schema/__init__.py
tonconsole/tonapi/schema/accounts.py
tonconsole/tonapi/schema/domains.py
tonconsole/tonapi/schema/jettons.py
tonconsole/tonapi/schema/nft.py
tonconsole/tonapi/schema/traces.py
tonconsole-0.0.25.dist-info/LICENSE
tonconsole-0.0.25.dist-info/METADATA
tonconsole-0.0.25.dist-info/WHEEL
tonconsole-0.0.25.dist-info/top_level.txt
tonconsole-0.0.25.dist-info/RECORD
