Metadata-Version: 2.1
Name: tonconsole
Version: 0.0.25
Summary: Connecting businesses to the TON ecosystem.
Home-page: https://github.com/nessshon/tonconsole/
Author: nessshon
License: UNKNOWN
Platform: UNKNOWN
Classifier: Programming Language :: Python :: 3
Classifier: License :: OSI Approved :: MIT License
Classifier: Operating System :: OS Independent
Requires-Python: >=3.10
License-File: LICENSE
Requires-Dist: aiohttp (>=3.8.3)
Requires-Dist: libscrc (>=1.8.1)
Requires-Dist: pydantic (>=1.10.4)
